setup.py
quiz/__init__.py
quiz/admin.py
quiz/forms.py
quiz/models.py
quiz/settings.py
quiz/signals.py
quiz/urls.py
quiz/views.py
simple_quiz.egg-info/PKG-INFO
simple_quiz.egg-info/SOURCES.txt
simple_quiz.egg-info/dependency_links.txt
simple_quiz.egg-info/not-zip-safe
simple_quiz.egg-info/requires.txt
simple_quiz.egg-info/top_level.txt