Metadata-Version: 1.1
Name: simple-quiz
Version: 0.6.1
Summary: A simple, multiple-guess Quiz app
Home-page: http://bitbucket.org/funkybob/simple-quiz/
Author: Curtis Maloney
Author-email: curtis@tinbrain.net
License: UNKNOWN
Keywords: django,quiz
Platform: UNKNOWN
Classifier: Environment :: Web Environment
Classifier: Framework :: Django
Classifier: License :: OSI Approved :: BSD License
Classifier: Operating System :: OS Independent
Classifier: Programming Language :: Python
